verified_email_change/__init__.py
verified_email_change/apps.py
verified_email_change/forms.py
verified_email_change/signals.py
verified_email_change/urls.py
verified_email_change/utils.py
verified_email_change/views.py
verified_email_change/templates/verified_email_change/change_email.html
verified_email_change/templates/verified_email_change/change_email_confirm.html
verified_email_change/templates/verified_email_change/change_email_confirmation_email.html
django_verified_email-0.1.1.dist-info/LICENSE
django_verified_email-0.1.1.dist-info/METADATA
django_verified_email-0.1.1.dist-info/WHEEL
django_verified_email-0.1.1.dist-info/top_level.txt
django_verified_email-0.1.1.dist-info/RECORD
