Metadata-Version: 2.1
Name: django-verified-email
Version: 0.1.1
Summary: Verified email changes for django
Home-page: UNKNOWN
Author: UNKNOWN
Author-email: UNKNOWN
License: BSD
Platform: UNKNOWN
Requires-Dist: Django (>=1.7)
Requires-Dist: django-absoluteuri
Requires-Dist: django-decoratormixins
Requires-Dist: django-ogmios
